{"cameraMode":{"drawMode":0,"name":"Shaded","section":"Shading Mode"},"sceneLighting":true,"audioPlay":false,"sceneViewState":{"m_AlwaysRefresh":false,"showFog":true,"showSkybox":true,"showFlares":true,"showImageEffects":true,"showParticleSystems":true,"showVisualEffectGraphs":true,"m_FxEnabled":true},"in2DMode":false,"pivot":{"x":0.040000006556510928,"y":0.5400000810623169,"z":0.0},"rotation":{"x":-0.0362987294793129,"y":-0.01439247652888298,"z":0.0005071288906037808,"w":-0.999249279499054},"size":0.5827980637550354,"orthographic":false}